topsis_harditya_102303230/__init__.py
topsis_harditya_102303230/main.py
topsis_harditya_102303230-0.1.0.dist-info/METADATA
topsis_harditya_102303230-0.1.0.dist-info/WHEEL
topsis_harditya_102303230-0.1.0.dist-info/entry_points.txt
topsis_harditya_102303230-0.1.0.dist-info/top_level.txt
topsis_harditya_102303230-0.1.0.dist-info/RECORD
