Metadata-Version: 2.4
Name: Topsis-Harditya-102303230
Version: 0.1.0
Summary: TOPSIS implementation with CLI support
Author: Harditya
Requires-Dist: numpy
Requires-Dist: pandas
Requires-Dist: openpyxl
Dynamic: author
Dynamic: requires-dist
Dynamic: summary
